LICENSE
MANIFEST.in
README
README.rst
RELEASE_NOTES.rst
VERSION
csv_to_xls.py
setup.py
csv2xls.egg-info/PKG-INFO
csv2xls.egg-info/SOURCES.txt
csv2xls.egg-info/dependency_links.txt
csv2xls.egg-info/entry_points.txt
csv2xls.egg-info/requires.txt
csv2xls.egg-info/top_level.txt
examples/gen_csv.py
examples/sheet_alpha.csv
examples/sheet_beta.csv
examples/sheet_delta.csv