Metadata-Version: 1.0
Name: csv2xls
Version: 0.4
Summary: Put together some CSV files into a single Excel file, in different sheets.
Home-page: https://github.com/alexprengere/csv2xls
Author: Alex Prengère
Author-email: alexprengere@gmail.com
License: Creative Commons
